MANIFEST.in
setup.py
trunity_importer/__init__.py
trunity_importer/utils.py
trunity_importer.egg-info/PKG-INFO
trunity_importer.egg-info/SOURCES.txt
trunity_importer.egg-info/dependency_links.txt
trunity_importer.egg-info/requires.txt
trunity_importer.egg-info/top_level.txt
trunity_importer/bin/trunity-importer
trunity_importer/qti/__init__.py
trunity_importer/qti/handlers.py
trunity_importer/qti/importer.py
trunity_importer/qti/parsers.py
trunity_importer/qti/tests/__init__.py
trunity_importer/qti/tests/test_parser.py
trunity_importer/qti/tests/data/essay.xml
trunity_importer/qti/tests/data/insmanifest.xml
trunity_importer/qti/tests/data/multiple_answer.xml
trunity_importer/qti/tests/data/multiple_choice.xml
trunity_importer/qti/tests/data/question_pool_meta_sample.xml
trunity_importer/qti/tests/data/question_with_flash_object.xml
trunity_importer/qti/tests/data/short_answer.xml
trunity_importer/sda/__init__.py
trunity_importer/sda/importer.py
trunity_importer/sda/parser.py
trunity_importer/sda/question_containers.py
trunity_importer/sda/question_handler.py
trunity_importer/sda/warnings.py
trunity_importer/sda/templates/question.html
trunity_importer/sda/tests/__init__.py
trunity_importer/sda/tests/test_parser.py
trunity_importer/sda/tests/test_post_validators.py
trunity_importer/sda/tests/test_question_handlers.py
trunity_importer/sda/tests/data/TechnologyEnhancedMultipleAnswer.json
trunity_importer/sda/tests/data/TechnologyEnhancedMultipleAnswer.xml
trunity_importer/sda/tests/data/XML_Export_sample.xml
trunity_importer/sda/tests/data/essay.xml
trunity_importer/sda/tests/data/multiple_choice.xml
trunity_importer/sda/validators/__init__.py
trunity_importer/sda/validators/post_validators.py
trunity_importer/sda/validators/pre_validators.py