Metadata-Version: 1.0
Name: trunity-importer
Version: 0.5.2
Summary: Library for importing content from various sources to Trunity 3 LMS.
Home-page: https://github.com/v-hunt/trunity-importer
Author: hunting
Author-email: VicHunting@yandex.ua
License: MIT
Platform: UNKNOWN
